MANIFEST.in
Makefile
README.md
setup.py
src/softsync/__init__.py
src/softsync/__main__.py
src/softsync/common.py
src/softsync/context.py
src/softsync/exception.py
src/softsync/scheme.py
src/softsync/sync.py
src/softsync.egg-info/PKG-INFO
src/softsync.egg-info/SOURCES.txt
src/softsync.egg-info/dependency_links.txt
src/softsync.egg-info/entry_points.txt
src/softsync.egg-info/requires.txt
src/softsync.egg-info/top_level.txt
src/softsync/commands/__init__.py
src/softsync/commands/cp.py
src/softsync/commands/ls.py
src/softsync/commands/repair.py
src/softsync/commands/rm.py